{
    "m_GameObject": {
        "m_FileID": 0,
        "m_PathID": 0
    },
    "m_Enabled": 1,
    "m_Script": {
        "m_FileID": 0,
        "m_PathID": 4652281892236711381
    },
    "m_Name": "PlaceData_D09R0101",
    "Data": [
        {
            "ID": "TR_ESPM_04",
            "zoneID": 244,
            "TrainerID": 166,
            "ObjectGraphicIndex": 57,
            "ColorIndex": 0,
            "Position": {
                "x": 7.0,
                "y": 69.0
            },
            "HeightLayer": 10,
            "HeightIgnore": 0,
            "Size": {
                "x": 0.0,
                "y": 0.0
            },
            "Rotation": 180,
            "MoveLimit": {
                "x": 0.0,
                "y": 0.0
            },
            "EventType": 1,
            "MoveCode": 7,
            "MoveParam0": 2,
            "MoveParam1": 0,
            "MoveParam2": 0,
            "TalkLabel": "ev_ESPM_04",
            "ContactLabel": "",
            "Work": 4000,
            "Dowsing": 0,
            "LoadFirst": 0,
            "DoNotLoad": 4000,
            "TalkToRange": 1.25,
            "TalkToSize": {
                "x": 0.0,
                "y": 0.0
            },
            "TalkBit": 15
        },
        {
            "ID": "TR_KARATE_17",
            "zoneID": 244,
            "TrainerID": 335,
            "ObjectGraphicIndex": 49,
            "ColorIndex": 0,
            "Position": {
                "x": 30.0,
                "y": 41.0
            },
            "HeightLayer": 10,
            "HeightIgnore": 0,
            "Size": {
                "x": 0.0,
                "y": 0.0
            },
            "Rotation": 0,
            "MoveLimit": {
                "x": 0.0,
                "y": 0.0
            },
            "EventType": 4,
            "MoveCode": 15,
            "MoveParam0": 1,
            "MoveParam1": 0,
            "MoveParam2": 0,
            "TalkLabel": "ev_KARATE_17",
            "ContactLabel": "",
            "Work": 4000,
            "Dowsing": 0,
            "LoadFirst": 0,
            "DoNotLoad": 4000,
            "TalkToRange": 1.25,
            "TalkToSize": {
                "x": 0.0,
                "y": 0.0
            },
            "TalkBit": 15
        },
        {
            "ID": "TR_BIRD_05",
            "zoneID": 244,
            "TrainerID": 165,
            "ObjectGraphicIndex": 75,
            "ColorIndex": 0,
            "Position": {
                "x": 31.0,
                "y": 58.0
            },
            "HeightLayer": 10,
            "HeightIgnore": 0,
            "Size": {
                "x": 0.0,
                "y": 0.0
            },
            "Rotation": 90,
            "MoveLimit": {
                "x": 0.0,
                "y": 0.0
            },
            "EventType": 1,
            "MoveCode": 16,
            "MoveParam0": 3,
            "MoveParam1": 0,
            "MoveParam2": 0,
            "TalkLabel": "ev_BIRD_05",
            "ContactLabel": "",
            "Work": 4000,
            "Dowsing": 0,
            "LoadFirst": 0,
            "DoNotLoad": 4000,
            "TalkToRange": 1.25,
            "TalkToSize": {
                "x": 0.0,
                "y": 0.0
            },
            "TalkBit": 15
        },
        {
            "ID": "TR_ELITEW_04",
            "zoneID": 244,
            "TrainerID": 158,
            "ObjectGraphicIndex": 39,
            "ColorIndex": 0,
            "Position": {
                "x": 10.0,
                "y": 42.0
            },
            "HeightLayer": 10,
            "HeightIgnore": 0,
            "Size": {
                "x": 0.0,
                "y": 0.0
            },
            "Rotation": 0,
            "MoveLimit": {
                "x": 0.0,
                "y": 0.0
            },
            "EventType": 1,
            "MoveCode": 15,
            "MoveParam0": 2,
            "MoveParam1": 0,
            "MoveParam2": 0,
            "TalkLabel": "ev_ELITEW_04",
            "ContactLabel": "",
            "Work": 4000,
            "Dowsing": 0,
            "LoadFirst": 0,
            "DoNotLoad": 4000,
            "TalkToRange": 1.25,
            "TalkToSize": {
                "x": 0.0,
                "y": 0.0
            },
            "TalkBit": 15
        },
        {
            "ID": "TR_VETERAN_05",
            "zoneID": 244,
            "TrainerID": 160,
            "ObjectGraphicIndex": 85,
            "ColorIndex": 0,
            "Position": {
                "x": 27.0,
                "y": 25.0
            },
            "HeightLayer": 10,
            "HeightIgnore": 0,
            "Size": {
                "x": 0.0,
                "y": 0.0
            },
            "Rotation": 270,
            "MoveLimit": {
                "x": 0.0,
                "y": 0.0
            },
            "EventType": 1,
            "MoveCode": 17,
            "MoveParam0": 2,
            "MoveParam1": 0,
            "MoveParam2": 0,
            "TalkLabel": "ev_VETERAN_05",
            "ContactLabel": "",
            "Work": 4000,
            "Dowsing": 0,
            "LoadFirst": 0,
            "DoNotLoad": 4000,
            "TalkToRange": 1.25,
            "TalkToSize": {
                "x": 0.0,
                "y": 0.0
            },
            "TalkBit": 15
        },
        {
            "ID": "TR_DRAGON_04",
            "zoneID": 244,
            "TrainerID": 163,
            "ObjectGraphicIndex": 74,
            "ColorIndex": 0,
            "Position": {
                "x": 40.0,
                "y": 31.0
            },
            "HeightLayer": 10,
            "HeightIgnore": 0,
            "Size": {
                "x": 0.0,
                "y": 0.0
            },
            "Rotation": 90,
            "MoveLimit": {
                "x": 0.0,
                "y": 0.0
            },
            "EventType": 1,
            "MoveCode": 16,
            "MoveParam0": 3,
            "MoveParam1": 0,
            "MoveParam2": 0,
            "TalkLabel": "ev_DRAGON_04",
            "ContactLabel": "",
            "Work": 4000,
            "Dowsing": 0,
            "LoadFirst": 0,
            "DoNotLoad": 4000,
            "TalkToRange": 1.25,
            "TalkToSize": {
                "x": 0.0,
                "y": 0.0
            },
            "TalkBit": 15
        },
        {
            "ID": "D09R0101_BIGMAN",
            "zoneID": 244,
            "TrainerID": 0,
            "ObjectGraphicIndex": -1,
            "ColorIndex": 0,
            "Position": {
                "x": 45.0,
                "y": 33.0
            },
            "HeightLayer": 10,
            "HeightIgnore": 0,
            "Size": {
                "x": 0.0,
                "y": 0.0
            },
            "Rotation": 90,
            "MoveLimit": {
                "x": 0.0,
                "y": 0.0
            },
            "EventType": 0,
            "MoveCode": 0,
            "MoveParam0": 0,
            "MoveParam1": 0,
            "MoveParam2": 0,
            "TalkLabel": "",
            "ContactLabel": "",
            "Work": 579,
            "Dowsing": 0,
            "LoadFirst": 0,
            "DoNotLoad": 4000,
            "TalkToRange": 1.25,
            "TalkToSize": {
                "x": 0.0,
                "y": 0.0
            },
            "TalkBit": 15
        },
        {
            "ID": "D09R0101_NURSE",
            "zoneID": 244,
            "TrainerID": 0,
            "ObjectGraphicIndex": 103,
            "ColorIndex": 0,
            "Position": {
                "x": 34.0,
                "y": 23.0
            },
            "HeightLayer": 10,
            "HeightIgnore": 0,
            "Size": {
                "x": 0.0,
                "y": 0.0
            },
            "Rotation": 90,
            "MoveLimit": {
                "x": 0.0,
                "y": 0.0
            },
            "EventType": 0,
            "MoveCode": 0,
            "MoveParam0": 0,
            "MoveParam1": 0,
            "MoveParam2": 0,
            "TalkLabel": "ev_d09r0101_nurse",
            "ContactLabel": "",
            "Work": 4000,
            "Dowsing": 0,
            "LoadFirst": 0,
            "DoNotLoad": 4000,
            "TalkToRange": 1.25,
            "TalkToSize": {
                "x": 0.0,
                "y": 0.0
            },
            "TalkBit": 15
        },
        {
            "ID": "D09R0101_NURSE2",
            "zoneID": 244,
            "TrainerID": 0,
            "ObjectGraphicIndex": 103,
            "ColorIndex": 0,
            "Position": {
                "x": 5.0,
                "y": 36.0
            },
            "HeightLayer": 99,
            "HeightIgnore": 0,
            "Size": {
                "x": 0.0,
                "y": 0.0
            },
            "Rotation": 0,
            "MoveLimit": {
                "x": 0.0,
                "y": 0.0
            },
            "EventType": 0,
            "MoveCode": 0,
            "MoveParam0": 0,
            "MoveParam1": 0,
            "MoveParam2": 0,
            "TalkLabel": "ev_d09r0101_nurse",
            "ContactLabel": "",
            "Work": 4000,
            "Dowsing": 0,
            "LoadFirst": 0,
            "DoNotLoad": 4000,
            "TalkToRange": 1.25,
            "TalkToSize": {
                "x": 0.0,
                "y": 0.0
            },
            "TalkBit": 15
        },
        {
            "ID": "D09R0101_BLOCKER",
            "zoneID": 244,
            "TrainerID": 0,
            "ObjectGraphicIndex": 129,
            "ColorIndex": 0,
            "Position": {
                "x": 38.0,
                "y": 17.0
            },
            "HeightLayer": 99,
            "HeightIgnore": 0,
            "Size": {
                "x": 0.0,
                "y": 0.0
            },
            "Rotation": 0,
            "MoveLimit": {
                "x": 0.0,
                "y": 0.0
            },
            "EventType": 0,
            "MoveCode": 0,
            "MoveParam0": 0,
            "MoveParam1": 0,
            "MoveParam2": 0,
            "TalkLabel": "ev_d09r0101_stopper_talk",
            "ContactLabel": "",
            "Work": 2777,
            "Dowsing": 0,
            "LoadFirst": 0,
            "DoNotLoad": 4000,
            "TalkToRange": 1.25,
            "TalkToSize": {
                "x": 0.0,
                "y": 0.0
            },
            "TalkBit": 15
        },
        {
            "ID": "D09R0101_BLOCKER_TRIGGER1",
            "zoneID": 244,
            "TrainerID": 0,
            "ObjectGraphicIndex": 670000,
            "ColorIndex": 0,
            "Position": {
                "x": 37.0,
                "y": 17.0
            },
            "HeightLayer": 99,
            "HeightIgnore": 1,
            "Size": {
                "x": 0.0,
                "y": 0.0
            },
            "Rotation": 0,
            "MoveLimit": {
                "x": 0.0,
                "y": 0.0
            },
            "EventType": 0,
            "MoveCode": 15,
            "MoveParam0": 0,
            "MoveParam1": 0,
            "MoveParam2": 0,
            "TalkLabel": "ev_d09r0101_stopper_talk_poke",
            "ContactLabel": "",
            "Work": 2777,
            "Dowsing": 0,
            "LoadFirst": 0,
            "DoNotLoad": 4000,
            "TalkToRange": 1.25,
            "TalkToSize": {
                "x": 0.0,
                "y": 0.0
            },
            "TalkBit": 15
        },
        {
            "ID": "D09R0101_BLOCKER_TRIGGER3",
            "zoneID": 244,
            "TrainerID": 0,
            "ObjectGraphicIndex": 670000,
            "ColorIndex": 0,
            "Position": {
                "x": 39.0,
                "y": 17.0
            },
            "HeightLayer": 99,
            "HeightIgnore": 1,
            "Size": {
                "x": 0.0,
                "y": 0.0
            },
            "Rotation": 0,
            "MoveLimit": {
                "x": 0.0,
                "y": 0.0
            },
            "EventType": 0,
            "MoveCode": 15,
            "MoveParam0": 0,
            "MoveParam1": 0,
            "MoveParam2": 0,
            "TalkLabel": "ev_d09r0101_stopper_talk_poke",
            "ContactLabel": "",
            "Work": 2777,
            "Dowsing": 0,
            "LoadFirst": 0,
            "DoNotLoad": 4000,
            "TalkToRange": 1.25,
            "TalkToSize": {
                "x": 0.0,
                "y": 0.0
            },
            "TalkBit": 15
        },
        {
            "ID": "D09R0101_ROCK_CLIMB1",
            "zoneID": 244,
            "TrainerID": 0,
            "ObjectGraphicIndex": -1,
            "ColorIndex": 0,
            "Position": {
                "x": 18.0,
                "y": 65.0
            },
            "HeightLayer": 1,
            "HeightIgnore": 1,
            "Size": {
                "x": 1.0,
                "y": 4.0
            },
            "Rotation": 0,
            "MoveLimit": {
                "x": 0.0,
                "y": 0.0
            },
            "EventType": 0,
            "MoveCode": 0,
            "MoveParam0": 0,
            "MoveParam1": 0,
            "MoveParam2": 0,
            "TalkLabel": "ev_hiden_kabenobori",
            "ContactLabel": "",
            "Work": 4000,
            "Dowsing": 0,
            "LoadFirst": 0,
            "DoNotLoad": 4000,
            "TalkToRange": 1.25,
            "TalkToSize": {
                "x": 0.0,
                "y": 0.0
            },
            "TalkBit": 15
        },
        {
            "ID": "D09R0101_ROCK_CLIMB2",
            "zoneID": 244,
            "TrainerID": 0,
            "ObjectGraphicIndex": -1,
            "ColorIndex": 0,
            "Position": {
                "x": 22.0,
                "y": 34.0
            },
            "HeightLayer": 1,
            "HeightIgnore": 1,
            "Size": {
                "x": 1.0,
                "y": 4.0
            },
            "Rotation": 0,
            "MoveLimit": {
                "x": 0.0,
                "y": 0.0
            },
            "EventType": 0,
            "MoveCode": 0,
            "MoveParam0": 0,
            "MoveParam1": 0,
            "MoveParam2": 0,
            "TalkLabel": "ev_hiden_kabenobori",
            "ContactLabel": "",
            "Work": 4000,
            "Dowsing": 0,
            "LoadFirst": 0,
            "DoNotLoad": 4000,
            "TalkToRange": 1.25,
            "TalkToSize": {
                "x": 0.0,
                "y": 0.0
            },
            "TalkBit": 15
        },
        {
            "ID": "D09R0101_ROCK_CLIMB3",
            "zoneID": 244,
            "TrainerID": 0,
            "ObjectGraphicIndex": -1,
            "ColorIndex": 0,
            "Position": {
                "x": 22.0,
                "y": 49.0
            },
            "HeightLayer": 1,
            "HeightIgnore": 1,
            "Size": {
                "x": 1.0,
                "y": 4.0
            },
            "Rotation": 0,
            "MoveLimit": {
                "x": 0.0,
                "y": 0.0
            },
            "EventType": 0,
            "MoveCode": 0,
            "MoveParam0": 0,
            "MoveParam1": 0,
            "MoveParam2": 0,
            "TalkLabel": "ev_hiden_kabenobori",
            "ContactLabel": "",
            "Work": 4000,
            "Dowsing": 0,
            "LoadFirst": 0,
            "DoNotLoad": 4000,
            "TalkToRange": 1.25,
            "TalkToSize": {
                "x": 0.0,
                "y": 0.0
            },
            "TalkBit": 15
        },
        {
            "ID": "D09R0101_ROCK_CLIMB4",
            "zoneID": 244,
            "TrainerID": 0,
            "ObjectGraphicIndex": -1,
            "ColorIndex": 0,
            "Position": {
                "x": 36.0,
                "y": 49.0
            },
            "HeightLayer": 1,
            "HeightIgnore": 1,
            "Size": {
                "x": 1.0,
                "y": 4.0
            },
            "Rotation": 0,
            "MoveLimit": {
                "x": 0.0,
                "y": 0.0
            },
            "EventType": 0,
            "MoveCode": 0,
            "MoveParam0": 0,
            "MoveParam1": 0,
            "MoveParam2": 0,
            "TalkLabel": "ev_hiden_kabenobori",
            "ContactLabel": "",
            "Work": 4000,
            "Dowsing": 0,
            "LoadFirst": 0,
            "DoNotLoad": 4000,
            "TalkToRange": 1.25,
            "TalkToSize": {
                "x": 0.0,
                "y": 0.0
            },
            "TalkBit": 15
        },
        {
            "ID": "D09R0101_ROCK_CLIMB5",
            "zoneID": 244,
            "TrainerID": 0,
            "ObjectGraphicIndex": -1,
            "ColorIndex": 0,
            "Position": {
                "x": 38.0,
                "y": 33.0
            },
            "HeightLayer": 1,
            "HeightIgnore": 1,
            "Size": {
                "x": 1.0,
                "y": 4.0
            },
            "Rotation": 0,
            "MoveLimit": {
                "x": 0.0,
                "y": 0.0
            },
            "EventType": 0,
            "MoveCode": 0,
            "MoveParam0": 0,
            "MoveParam1": 0,
            "MoveParam2": 0,
            "TalkLabel": "ev_hiden_kabenobori",
            "ContactLabel": "",
            "Work": 4000,
            "Dowsing": 0,
            "LoadFirst": 0,
            "DoNotLoad": 4000,
            "TalkToRange": 1.25,
            "TalkToSize": {
                "x": 0.0,
                "y": 0.0
            },
            "TalkBit": 15
        },
        {
            "ID": "FLD_ITEM_66",
            "zoneID": 244,
            "TrainerID": 0,
            "ObjectGraphicIndex": 500,
            "ColorIndex": 0,
            "Position": {
                "x": 42.0,
                "y": 48.0
            },
            "HeightLayer": 6,
            "HeightIgnore": 0,
            "Size": {
                "x": 0.0,
                "y": 0.0
            },
            "Rotation": 0,
            "MoveLimit": {
                "x": 0.0,
                "y": 0.0
            },
            "EventType": 0,
            "MoveCode": 0,
            "MoveParam0": 0,
            "MoveParam1": 0,
            "MoveParam2": 0,
            "TalkLabel": "ev_fld_item_66",
            "ContactLabel": "",
            "Work": 921,
            "Dowsing": 0,
            "LoadFirst": 0,
            "DoNotLoad": 4000,
            "TalkToRange": 1.25,
            "TalkToSize": {
                "x": 0.0,
                "y": 0.0
            },
            "TalkBit": 15
        },
        {
            "ID": "FLD_ITEM_67",
            "zoneID": 244,
            "TrainerID": 0,
            "ObjectGraphicIndex": 500,
            "ColorIndex": 0,
            "Position": {
                "x": 28.0,
                "y": 46.0
            },
            "HeightLayer": 6,
            "HeightIgnore": 0,
            "Size": {
                "x": 0.0,
                "y": 0.0
            },
            "Rotation": 0,
            "MoveLimit": {
                "x": 0.0,
                "y": 0.0
            },
            "EventType": 0,
            "MoveCode": 0,
            "MoveParam0": 0,
            "MoveParam1": 0,
            "MoveParam2": 0,
            "TalkLabel": "ev_fld_item_67",
            "ContactLabel": "",
            "Work": 922,
            "Dowsing": 0,
            "LoadFirst": 0,
            "DoNotLoad": 4000,
            "TalkToRange": 1.25,
            "TalkToSize": {
                "x": 0.0,
                "y": 0.0
            },
            "TalkBit": 15
        },
        {
            "ID": "FLD_ITEM_68",
            "zoneID": 244,
            "TrainerID": 0,
            "ObjectGraphicIndex": 500,
            "ColorIndex": 0,
            "Position": {
                "x": 7.0,
                "y": 61.0
            },
            "HeightLayer": 6,
            "HeightIgnore": 0,
            "Size": {
                "x": 0.0,
                "y": 0.0
            },
            "Rotation": 0,
            "MoveLimit": {
                "x": 0.0,
                "y": 0.0
            },
            "EventType": 0,
            "MoveCode": 0,
            "MoveParam0": 0,
            "MoveParam1": 0,
            "MoveParam2": 0,
            "TalkLabel": "ev_fld_item_68",
            "ContactLabel": "",
            "Work": 923,
            "Dowsing": 0,
            "LoadFirst": 0,
            "DoNotLoad": 4000,
            "TalkToRange": 1.25,
            "TalkToSize": {
                "x": 0.0,
                "y": 0.0
            },
            "TalkBit": 15
        },
        {
            "ID": "FLD_ITEM_69",
            "zoneID": 244,
            "TrainerID": 0,
            "ObjectGraphicIndex": 500,
            "ColorIndex": 0,
            "Position": {
                "x": 13.0,
                "y": 38.0
            },
            "HeightLayer": 6,
            "HeightIgnore": 0,
            "Size": {
                "x": 0.0,
                "y": 0.0
            },
            "Rotation": 0,
            "MoveLimit": {
                "x": 0.0,
                "y": 0.0
            },
            "EventType": 0,
            "MoveCode": 0,
            "MoveParam0": 0,
            "MoveParam1": 0,
            "MoveParam2": 0,
            "TalkLabel": "ev_fld_item_69",
            "ContactLabel": "",
            "Work": 924,
            "Dowsing": 0,
            "LoadFirst": 0,
            "DoNotLoad": 4000,
            "TalkToRange": 1.25,
            "TalkToSize": {
                "x": 0.0,
                "y": 0.0
            },
            "TalkBit": 15
        },
        {
            "ID": "FLD_ITEM_70",
            "zoneID": 244,
            "TrainerID": 0,
            "ObjectGraphicIndex": 500,
            "ColorIndex": 0,
            "Position": {
                "x": 44.0,
                "y": 36.0
            },
            "HeightLayer": 6,
            "HeightIgnore": 0,
            "Size": {
                "x": 0.0,
                "y": 0.0
            },
            "Rotation": 0,
            "MoveLimit": {
                "x": 0.0,
                "y": 0.0
            },
            "EventType": 0,
            "MoveCode": 0,
            "MoveParam0": 0,
            "MoveParam1": 0,
            "MoveParam2": 0,
            "TalkLabel": "ev_fld_item_70",
            "ContactLabel": "",
            "Work": 1036,
            "Dowsing": 0,
            "LoadFirst": 0,
            "DoNotLoad": 4000,
            "TalkToRange": 1.25,
            "TalkToSize": {
                "x": 0.0,
                "y": 0.0
            },
            "TalkBit": 15
        },
        {
            "ID": "FLD_HIDE_ITEM_64",
            "zoneID": 244,
            "TrainerID": 0,
            "ObjectGraphicIndex": -1,
            "ColorIndex": 0,
            "Position": {
                "x": 36.0,
                "y": 41.0
            },
            "HeightLayer": 99,
            "HeightIgnore": 0,
            "Size": {
                "x": 0.0,
                "y": 0.0
            },
            "Rotation": 0,
            "MoveLimit": {
                "x": 0.0,
                "y": 0.0
            },
            "EventType": 0,
            "MoveCode": 0,
            "MoveParam0": 0,
            "MoveParam1": 0,
            "MoveParam2": 0,
            "TalkLabel": "ev_hide_item_64",
            "ContactLabel": "",
            "Work": 667,
            "Dowsing": 1,
            "LoadFirst": 0,
            "DoNotLoad": 4000,
            "TalkToRange": 1.25,
            "TalkToSize": {
                "x": 0.0,
                "y": 0.0
            },
            "TalkBit": 15
        },
        {
            "ID": "FLD_HIDE_ITEM_65",
            "zoneID": 244,
            "TrainerID": 0,
            "ObjectGraphicIndex": -1,
            "ColorIndex": 0,
            "Position": {
                "x": 20.0,
                "y": 32.0
            },
            "HeightLayer": 99,
            "HeightIgnore": 0,
            "Size": {
                "x": 0.0,
                "y": 0.0
            },
            "Rotation": 0,
            "MoveLimit": {
                "x": 0.0,
                "y": 0.0
            },
            "EventType": 0,
            "MoveCode": 0,
            "MoveParam0": 0,
            "MoveParam1": 0,
            "MoveParam2": 0,
            "TalkLabel": "ev_hide_item_65",
            "ContactLabel": "",
            "Work": 668,
            "Dowsing": 1,
            "LoadFirst": 0,
            "DoNotLoad": 4000,
            "TalkToRange": 1.25,
            "TalkToSize": {
                "x": 0.0,
                "y": 0.0
            },
            "TalkBit": 15
        },
        {
            "ID": "FLD_HIDE_ITEM_66",
            "zoneID": 244,
            "TrainerID": 0,
            "ObjectGraphicIndex": -1,
            "ColorIndex": 0,
            "Position": {
                "x": 10.0,
                "y": 26.0
            },
            "HeightLayer": 99,
            "HeightIgnore": 0,
            "Size": {
                "x": 0.0,
                "y": 0.0
            },
            "Rotation": 0,
            "MoveLimit": {
                "x": 0.0,
                "y": 0.0
            },
            "EventType": 0,
            "MoveCode": 0,
            "MoveParam0": 0,
            "MoveParam1": 0,
            "MoveParam2": 0,
            "TalkLabel": "ev_hide_item_66",
            "ContactLabel": "",
            "Work": 669,
            "Dowsing": 1,
            "LoadFirst": 0,
            "DoNotLoad": 4000,
            "TalkToRange": 1.25,
            "TalkToSize": {
                "x": 0.0,
                "y": 0.0
            },
            "TalkBit": 15
        }
    ]
}